{
  "workspace": "max_of_three",
  "stage": "verify",
  "input_c": "original/max_of_three.c",
  "input_v": "",
  "original_c": "original/max_of_three.c",
  "original_v": "",
  "annotated_c": "annotated/max_of_three.c",
  "function_name": "max_of_three",
  "semantic_description": "Computes and returns the maximum of three scalar integer inputs using straight-line initialization followed by two conditional branches. The result must be one of the original inputs and must be greater than or equal to all three original inputs. The function performs no heap or pointer memory updates.",
  "keywords": {
    "algorithm_family": "selection",
    "control_flow": [
      "straight_line",
      "if"
    ],
    "data_shape": "scalar_only",
    "semantic_intent": "return_max",
    "proof_pattern": [
      "pure_arithmetic",
      "case_split"
    ],
    "edge_case_behavior": "branch_on_order",
    "verification_status": [
      "goal_check_passed",
      "auto_proof_contains_admitted"
    ]
  },
  "assume_contract_is_correct": true,
  "contract_source": "contract_input_c"
}
